parsers/ base_parser.py
parsers/__init__.py
parsers/python_parser.py
refactoring_assistant-0.1.0.dist-info/METADATA
refactoring_assistant-0.1.0.dist-info/WHEEL
refactoring_assistant-0.1.0.dist-info/top_level.txt
refactoring_assistant-0.1.0.dist-info/RECORD
