Metadata-Version: 2.1
Name: refactoring_assistant
Version: 0.1.0
Summary: Библиотека для выявления участков кода, требующих рефакторинга
Home-page: https://github.com/username/refactoring-assistant
Author: Ruslan
Author-email: Waiper@gmail.com
Classifier: Programming Language :: Python :: 3
Classifier: License :: OSI Approved :: MIT License
Classifier: Operating System :: OS Independent
Requires-Python: >=3.6
